mofa/__init__.py
mofa/cli.py
mofa/agent-template/cookiecutter.json
mofa/agent-template/{{ cookiecutter.user_agent_dir }}/.gitignore
mofa/agent-template/{{ cookiecutter.user_agent_dir }}/README.md
mofa/agent-template/{{ cookiecutter.user_agent_dir }}/pyproject.toml
mofa/agent-template/{{ cookiecutter.user_agent_dir }}/tests/test_main.py
mofa/agent-template/{{ cookiecutter.user_agent_dir }}/{{ cookiecutter.agent_name }}/__init__.py
mofa/agent-template/{{ cookiecutter.user_agent_dir }}/{{ cookiecutter.agent_name }}/main.py
mofa/agent-template/{{ cookiecutter.user_agent_dir }}/{{ cookiecutter.agent_name }}/configs/agent.yml
mofa/agent_build/__init__.py
mofa/agent_build/base/__init__.py
mofa/agent_build/base/base_agent.py
mofa/commands/__init__.py
mofa/commands/config.py
mofa/commands/init.py
mofa/commands/run_flow.py
mofa/commands/search.py
mofa/commands/vibe.py
mofa/debug/__init__.py
mofa/debug/actor.py
mofa/debug/gen_reporter.py
mofa/debug/iteractive.py
mofa/debug/load_node.py
mofa/debug/parse_test_case.py
mofa/kernel/__init__.py
mofa/kernel/base.py
mofa/registry/__init__.py
mofa/registry/hub.py
mofa/utils/__init__.py
mofa/utils/ai/__init__.py
mofa/utils/ai/conn.py
mofa/utils/date/__init__.py
mofa/utils/date/util.py
mofa/utils/envs/__init__.py
mofa/utils/envs/util.py
mofa/utils/files/__init__.py
mofa/utils/files/delete.py
mofa/utils/files/dir.py
mofa/utils/files/read.py
mofa/utils/files/util.py
mofa/utils/files/write.py
mofa/utils/func/__init__.py
mofa/utils/func/util.py
mofa/utils/install_pkg/__init__.py
mofa/utils/install_pkg/load_task_weaver_result.py
mofa/utils/log/__init__.py
mofa/utils/log/agent.py
mofa/utils/log/autogen.py
mofa/utils/process/__init__.py
mofa/utils/process/util.py
mofa/utils/search/__init__.py
mofa/utils/search/util.py
mofa/utils/variable/__init__.py
mofa/utils/variable/util.py
mofa/vibe/__init__.py
mofa/vibe/debug_runner.py
mofa/vibe/engine.py
mofa/vibe/flow_generator.py
mofa/vibe/flow_scaffolder.py
mofa/vibe/llm_client.py
mofa/vibe/models.py
mofa_core-0.1.35.dist-info/licenses/LICENSE
mofa_core-0.1.35.dist-info/METADATA
mofa_core-0.1.35.dist-info/WHEEL
mofa_core-0.1.35.dist-info/entry_points.txt
mofa_core-0.1.35.dist-info/top_level.txt
mofa_core-0.1.35.dist-info/RECORD
