Metadata-Version: 2.4
Name: mofa-core
Version: 0.1.35
Summary: MoFA is a software framework for building AI agents through a composition-based approach.
Author: Cheng Chen, ZongHuan Wu
Author-email: chenzi00103@gmail.com, zonghuan.wu@gmail.com
Keywords: mofa ai agents dataflow composition
Classifier: Development Status :: 4 - Beta
Classifier: Intended Audience :: Developers
Classifier: Natural Language :: English
Classifier: Programming Language :: Python :: 3.10
Classifier: Programming Language :: Python :: 3.11
Classifier: Programming Language :: Python :: 3.12
Requires-Python: >=3.10
License-File: LICENSE
Requires-Dist: pendulum>=3.0.0
Requires-Dist: python-dotenv==1.0.1
Requires-Dist: cookiecutter>=2.0.0
Requires-Dist: click>=8.0.0
Requires-Dist: openpyxl==3.1.5
Requires-Dist: attrs<26,>=25.1.0
Requires-Dist: rich>=13.0.0
Requires-Dist: openai==1.65.4
Requires-Dist: instructor<2.0.0,>=1.8.0
Requires-Dist: mem0ai>=0.1.0
Requires-Dist: pandas>=2.0.0
Requires-Dist: pyarrow>=17.0.0
Requires-Dist: pyyaml
Requires-Dist: toml
Requires-Dist: mcp<2.0.0,>=1.9.0
Requires-Dist: fastmcp<3.0.0,>=2.2.0
Requires-Dist: dora-rs-cli>=0.3.0
Dynamic: author
Dynamic: author-email
Dynamic: classifier
Dynamic: description
Dynamic: description-content-type
Dynamic: keywords
Dynamic: license-file
Dynamic: requires-dist
Dynamic: requires-python
Dynamic: summary
